{"cameraMode":{"drawMode":0,"name":"Shaded","section":"Shading Mode"},"sceneLighting":true,"audioPlay":false,"sceneViewState":{"showFog":true,"showMaterialUpdate":false,"showSkybox":true,"showFlares":true,"showImageEffects":true,"showParticleSystems":true},"in2DMode":false,"pivot":{"x":-8.821174621582032,"y":4.8581223487854,"z":-0.9014073014259338},"rotation":{"x":-0.07155293971300125,"y":-0.5292071104049683,"z":0.04443484544754028,"w":-0.8445513844490051},"size":7.5941314697265629,"orthographic":false}